metamorphic_guard/__init__.py
metamorphic_guard/adaptive.py
metamorphic_guard/adaptive_sampling.py
metamorphic_guard/agent_tracing.py
metamorphic_guard/api.py
metamorphic_guard/audit.py
metamorphic_guard/audit_enhanced.py
metamorphic_guard/budget_aware_execution.py
metamorphic_guard/bundle.py
metamorphic_guard/cli.py
metamorphic_guard/compliance.py
metamorphic_guard/config.py
metamorphic_guard/cost_estimation.py
metamorphic_guard/dispatch.py
metamorphic_guard/dispatch_queue.py
metamorphic_guard/early_stopping.py
metamorphic_guard/errors.py
metamorphic_guard/gate.py
metamorphic_guard/generators.py
metamorphic_guard/harness.py
metamorphic_guard/heartbeat_manager.py
metamorphic_guard/junit.py
metamorphic_guard/llm_harness.py
metamorphic_guard/llm_specs.py
metamorphic_guard/logging.py
metamorphic_guard/memory_optimization.py
metamorphic_guard/model_comparison.py
metamorphic_guard/model_registry.py
metamorphic_guard/monitoring.py
metamorphic_guard/multi_objective.py
metamorphic_guard/multiple_comparisons.py
metamorphic_guard/notifications.py
metamorphic_guard/observability.py
metamorphic_guard/plugins.py
metamorphic_guard/policy.py
metamorphic_guard/power.py
metamorphic_guard/profiling.py
metamorphic_guard/queue_adapter.py
metamorphic_guard/queue_serialization.py
metamorphic_guard/redaction.py
metamorphic_guard/relations.py
metamorphic_guard/report_schema.py
metamorphic_guard/reporting.py
metamorphic_guard/result_cache.py
metamorphic_guard/risk_monitoring.py
metamorphic_guard/safety_monitors.py
metamorphic_guard/sandbox.py
metamorphic_guard/sandbox_cache.py
metamorphic_guard/sandbox_limits.py
metamorphic_guard/sandbox_workspace.py
metamorphic_guard/scalability.py
metamorphic_guard/sequential_testing.py
metamorphic_guard/shrink.py
metamorphic_guard/specs.py
metamorphic_guard/stability.py
metamorphic_guard/stability_audit.py
metamorphic_guard/telemetry.py
metamorphic_guard/tradeoff_visualization.py
metamorphic_guard/trust_scoring.py
metamorphic_guard/types.py
metamorphic_guard-3.3.5.dist-info/licenses/LICENSE
metamorphic_guard-3.3.5.dist-info/METADATA
metamorphic_guard-3.3.5.dist-info/WHEEL
metamorphic_guard-3.3.5.dist-info/entry_points.txt
metamorphic_guard-3.3.5.dist-info/top_level.txt
metamorphic_guard-3.3.5.dist-info/RECORD
