Metadata-Version: 2.4
Name: metamorphic_guard
Version: 3.3.5
Summary: A Python library for comparing program versions using metamorphic testing
Author: Spencer Duh
License-Expression: MIT
Project-URL: Homepage, https://github.com/duhboto/MetamorphicGuard
Project-URL: Bug Tracker, https://github.com/duhboto/MetamorphicGuard/issues
Project-URL: Documentation, https://pypi.org/project/metamorphic-guard/
Classifier: Programming Language :: Python :: 3
Classifier: Programming Language :: Python :: 3.10
Classifier: Programming Language :: Python :: 3.11
Classifier: Programming Language :: Python :: 3.12
Classifier: Operating System :: OS Independent
Classifier: Intended Audience :: Developers
Classifier: Topic :: Software Development :: Testing
Requires-Python: >=3.10
License-File: LICENSE
Requires-Dist: click>=8.1
Requires-Dist: pydantic>=2.0
Provides-Extra: dev
Requires-Dist: pytest>=7.0.0; extra == "dev"
Requires-Dist: pytest-timeout>=2.1.0; extra == "dev"
Requires-Dist: pytest-cov>=4.0.0; extra == "dev"
Requires-Dist: coverage[toml]>=7.0.0; extra == "dev"
Requires-Dist: hypothesis>=6.0.0; extra == "dev"
Requires-Dist: mypy>=1.10.0; extra == "dev"
Provides-Extra: llm
Requires-Dist: openai>=1.0.0; extra == "llm"
Requires-Dist: anthropic>=0.18.0; extra == "llm"
Requires-Dist: vllm>=0.2.0; extra == "llm"
Provides-Extra: otel
Requires-Dist: opentelemetry-api>=1.20.0; extra == "otel"
Requires-Dist: opentelemetry-sdk>=1.20.0; extra == "otel"
Requires-Dist: opentelemetry-exporter-otlp-proto-grpc>=1.20.0; extra == "otel"
Provides-Extra: queue
Requires-Dist: redis>=5.0.0; extra == "queue"
Requires-Dist: boto3>=1.28.0; extra == "queue"
Requires-Dist: pika>=1.3.0; extra == "queue"
Requires-Dist: kafka-python>=2.0.0; extra == "queue"
Provides-Extra: docs
Requires-Dist: mkdocs>=1.5.0; extra == "docs"
Requires-Dist: mkdocs-material>=9.0.0; extra == "docs"
Requires-Dist: mkdocstrings[python]>=0.24.0; extra == "docs"
Requires-Dist: pymdown-extensions>=10.0.0; extra == "docs"
Provides-Extra: all
Requires-Dist: openai>=1.0.0; extra == "all"
Requires-Dist: anthropic>=0.18.0; extra == "all"
Requires-Dist: vllm>=0.2.0; extra == "all"
Requires-Dist: opentelemetry-api>=1.20.0; extra == "all"
Requires-Dist: opentelemetry-sdk>=1.20.0; extra == "all"
Requires-Dist: opentelemetry-exporter-otlp-proto-grpc>=1.20.0; extra == "all"
Requires-Dist: redis>=5.0.0; extra == "all"
Requires-Dist: boto3>=1.28.0; extra == "all"
Requires-Dist: pika>=1.3.0; extra == "all"
Requires-Dist: kafka-python>=2.0.0; extra == "all"
Requires-Dist: mkdocs>=1.5.0; extra == "all"
Requires-Dist: mkdocs-material>=9.0.0; extra == "all"
Requires-Dist: mkdocstrings[python]>=0.24.0; extra == "all"
Requires-Dist: pymdown-extensions>=10.0.0; extra == "all"
Dynamic: license-file
